servicestack/__init__.py
servicestack/clients.py
servicestack/fields.py
servicestack/log.py
servicestack/reflection.py
servicestack/types.py
servicestack/utils.py
servicestack-0.1.15.dist-info/licenses/LICENSE
tests/__init__.py
tests/aiserver_dtos.py
tests/config.py
tests/dtos.py
tests/techstacks_dtos.py
tests/test_aiserver.py
tests/test_client.py
tests/test_client_auth.py
tests/test_client_utils.py
tests/test_enum_serialization.py
tests/test_inspect.py
tests/test_jsonserviceclient.py
tests/test_serialization.py
tests/test_techstacks.py
servicestack-0.1.15.dist-info/METADATA
servicestack-0.1.15.dist-info/WHEEL
servicestack-0.1.15.dist-info/top_level.txt
servicestack-0.1.15.dist-info/RECORD
