Metadata-Version: 2.4
Name: servicestack
Version: 0.1.15
Summary: ServiceStack Python Service Clients
Home-page: https://github.com/ServiceStack/servicestack-python
Author: ServiceStack, Inc.
Author-email: team@servicestack.net
License: BSD-3-Clause
Keywords: servicestack,client,dotnet
Classifier: Intended Audience :: Developers
Classifier: License :: OSI Approved :: BSD License
Classifier: Natural Language :: English
Classifier: Operating System :: OS Independent
Classifier: Programming Language :: Python :: 3.7
Classifier: Programming Language :: Python :: 3.8
Classifier: Programming Language :: Python :: 3.9
Classifier: Topic :: Software Development :: Libraries :: Python Modules
Requires-Python: >=3.7
License-File: LICENSE
Requires-Dist: typing_extensions>=3.7.4
Requires-Dist: requests>=2.23.0
Requires-Dist: dataclasses>=0.6
Requires-Dist: dataclasses-json>=0.5.4
Requires-Dist: marshmallow>=3.12.2
Dynamic: author
Dynamic: author-email
Dynamic: classifier
Dynamic: description
Dynamic: description-content-type
Dynamic: home-page
Dynamic: keywords
Dynamic: license
Dynamic: license-file
Dynamic: requires-dist
Dynamic: requires-python
Dynamic: summary
